odoo/addons/account_payment_return_import_iso20022/README.rst
odoo/addons/account_payment_return_import_iso20022/__init__.py
odoo/addons/account_payment_return_import_iso20022/__manifest__.py
odoo/addons/account_payment_return_import_iso20022/data/payment.return.reason.csv
odoo/addons/account_payment_return_import_iso20022/i18n/account_payment_return_import_iso20022.pot
odoo/addons/account_payment_return_import_iso20022/models/__init__.py
odoo/addons/account_payment_return_import_iso20022/models/payment_return.py
odoo/addons/account_payment_return_import_iso20022/readme/CONTRIBUTORS.rst
odoo/addons/account_payment_return_import_iso20022/readme/DESCRIPTION.rst
odoo/addons/account_payment_return_import_iso20022/readme/INSTALL.rst
odoo/addons/account_payment_return_import_iso20022/static/description/icon.png
odoo/addons/account_payment_return_import_iso20022/static/description/index.html
odoo/addons/account_payment_return_import_iso20022/test_files/test-sepa-camt-unpaid-invalid.xml
odoo/addons/account_payment_return_import_iso20022/test_files/test-sepa-camt-unpaid.xml
odoo/addons/account_payment_return_import_iso20022/test_files/test-sepa-camt-unpaid.zip
odoo/addons/account_payment_return_import_iso20022/test_files/test-sepa-pain-unpaid-invalid.xml
odoo/addons/account_payment_return_import_iso20022/test_files/test-sepa-pain-unpaid.xml
odoo/addons/account_payment_return_import_iso20022/test_files/test-sepa-pain-unpaid.zip
odoo/addons/account_payment_return_import_iso20022/tests/__init__.py
odoo/addons/account_payment_return_import_iso20022/tests/test_import_iso20022.py
odoo/addons/account_payment_return_import_iso20022/wizard/__init__.py
odoo/addons/account_payment_return_import_iso20022/wizard/camt_parser.py
odoo/addons/account_payment_return_import_iso20022/wizard/pain_parser.py
odoo/addons/account_payment_return_import_iso20022/wizard/payment_return_import.py
odoo12_addon_account_payment_return_import_iso20022-12.0.1.1.0.dist-info/METADATA
odoo12_addon_account_payment_return_import_iso20022-12.0.1.1.0.dist-info/RECORD
odoo12_addon_account_payment_return_import_iso20022-12.0.1.1.0.dist-info/WHEEL
odoo12_addon_account_payment_return_import_iso20022-12.0.1.1.0.dist-info/top_level.txt
