Metadata-Version: 2.1
Name: odoo12-addon-account-payment-return-import-iso20022
Version: 12.0.1.1.0
Summary: This addon allows to import payment returns from ISO 20022 files
Home-page: https://github.com/OCA/account-payment/tree/12.0/account_payment_return_import_iso20022
Author: Odoo Community Association (OCA),Tecnativa,ACSONE SA/NV
Author-email: support@odoo-community.org
License: AGPL-3
Platform: UNKNOWN
Classifier: Programming Language :: Python
Classifier: Framework :: Odoo
Classifier: License :: OSI Approved :: GNU Affero General Public License v3
Classifier: Development Status :: 5 - Production/Stable
Requires-Python: >=3.5
Requires-Dist: odoo12-addon-account-payment-order
Requires-Dist: odoo12-addon-account-payment-return
Requires-Dist: odoo12-addon-account-payment-return-import
Requires-Dist: odoo (<12.1dev,>=12.0a)
